model_version/__init__.py
model_version/model.py
model_version/settings.py
model_version/utils.py
model_version-0.2.2.dist-info/LICENSE
model_version-0.2.2.dist-info/METADATA
model_version-0.2.2.dist-info/WHEEL
model_version-0.2.2.dist-info/RECORD
