Metadata-Version: 2.1
Name: model-version
Version: 0.2.2
Summary: Django model version mixin
Home-page: https://github.com/aleosd/model-version
License: Apache-2.0
Keywords: django,model,version
Author: Alex
Author-email: osdalex@gmail.com
Requires-Python: >=3.8,<4.0
Classifier: Development Status :: 3 - Alpha
Classifier: Framework :: Django
Classifier: Intended Audience :: Developers
Classifier: License :: OSI Approved :: Apache Software License
Classifier: License :: OSI Approved :: GNU General Public License v3 or later (GPLv3+)
Classifier: Programming Language :: Python :: 3
Classifier: Programming Language :: Python :: 3.8
Classifier: Programming Language :: Python :: 3.9
Classifier: Programming Language :: Python :: 3.10
Classifier: Programming Language :: Python :: 3.11
Classifier: Programming Language :: Python :: 3.12
Requires-Dist: Django (>=3.0.0,<5.0.0)
Project-URL: Documentation, https://github.com/aleosd/model-version
Project-URL: Repository, https://github.com/aleosd/model-version.git
